novation_launchpad/__init__.py
novation_launchpad/charset.py
novation_launchpad/launchpad.py
novation_launchpad-1.0.0.dist-info/LICENSE
novation_launchpad-1.0.0.dist-info/METADATA
novation_launchpad-1.0.0.dist-info/WHEEL
novation_launchpad-1.0.0.dist-info/top_level.txt
novation_launchpad-1.0.0.dist-info/RECORD
