Metadata-Version: 2.1
Name: novation-launchpad
Version: 1.0.0
Summary: A Python library for launchpad mini, mk2 and pro devices with examples.
Home-page: https://github.com/eavelardev/novation-launchpad
Author: Eduardo Avelar
Author-email: eavelardev@gmail.com
License: UNKNOWN
Platform: UNKNOWN
Classifier: Programming Language :: Python :: 3
Classifier: License :: OSI Approved :: GNU General Public License v3 (GPLv3)
Classifier: Operating System :: OS Independent
Requires-Dist: python-rtmidi
